stix_parser/__init__.py
stix_parser/analysis/__init__.py
stix_parser/analysis/calibration.py
stix_parser/analysis/calibration_root.py
stix_parser/analysis/detector_test.py
stix_parser/analysis/housekeeping.py
stix_parser/analysis/ql_lightcurve.py
stix_parser/analysis/quick_processing.py
stix_parser/analysis/quicklook.py
stix_parser/analysis/test_analyzer.py
stix_parser/apps/__init__.py
stix_parser/apps/clipboard_hex_to_bin.py
stix_parser/apps/dump_socket_tk.py
stix_parser/apps/export_mib_to_sqlite.py
stix_parser/apps/mongodb_benchmark.py
stix_parser/apps/packet_filter.py
stix_parser/apps/packet_stat.py
stix_parser/apps/parameter_description.py
stix_parser/apps/parser.py
stix_parser/apps/pklz_view.py
stix_parser/apps/read_aspect_data.py
stix_parser/apps/read_mongodb.py
stix_parser/apps/soc_ascii_parser.py
stix_parser/apps/soc_xml_parser.py
stix_parser/apps/socket_dump.py
stix_parser/apps/stix_parser_gui.py
stix_parser/apps/stix_quicklook.py
stix_parser/apps/stix_xml_to_bin.py
stix_parser/core/__init__.py
stix_parser/core/mongo_db.py
stix_parser/core/stix_S20_parser.py
stix_parser/core/stix_context.py
stix_parser/core/stix_datetime.py
stix_parser/core/stix_decompressor.py
stix_parser/core/stix_global.py
stix_parser/core/stix_header.py
stix_parser/core/stix_idb.py
stix_parser/core/stix_logger.py
stix_parser/core/stix_packet_analyzer.py
stix_parser/core/stix_parameter.py
stix_parser/core/stix_parser.py
stix_parser/core/stix_sci_report_analyzer.py
stix_parser/core/stix_writer.py
stix_parser/ui/__init__.py
stix_parser/ui/mainwindow.py
stix_parser/ui/mainwindow_rc5.py
stix_parser/ui/mongo_db.py
stix_parser/ui/mongo_dialog.py
stix_parser/ui/packet_filter.py
stix_parser/ui/parser_gui.py
stix_parser/ui/parser_gui_packetArrival.py
stix_parser/ui/plugin.py
stix_parser/ui/raw_viewer.py
stix_parser/ui/tsc_connection.py
stix_parser-1.4.data/data/idb/idb.sqlite
stix_parser-1.4.dist-info/LICENSE
stix_parser-1.4.dist-info/METADATA
stix_parser-1.4.dist-info/WHEEL
stix_parser-1.4.dist-info/entry_points.txt
stix_parser-1.4.dist-info/top_level.txt
stix_parser-1.4.dist-info/RECORD
