Metadata-Version: 2.1
Name: stix-parser
Version: 1.4
Summary: STIX python data parser
Home-page: https://github.com/i4Ds/STIX-python-data-parser
Author: Hualin Xiao
Author-email: hualin.xiao@fhnw.ch
License: UNKNOWN
Platform: UNKNOWN
Requires-Python: >=3.6
Requires-Dist: numpy
Requires-Dist: PyQt5
Requires-Dist: PyQtChart
Requires-Dist: scipy
Requires-Dist: pymongo
Requires-Dist: python-dateutil
Requires-Dist: xmltodict
